{
  "running": true,
  "startTime": "2026-04-17T16:17:07.404Z",
  "total": 106,
  "passed": 86,
  "failed": 9,
  "skipped": 8,
  "currentTest": null,
  "recentTests": [
    {
      "title": "sonrie: Sin imágenes rotas en catálogo @catalog @calidad",
      "status": "passed",
      "duration": 9387
    },
    {
      "title": "sonrie: Pipeline API catálogo devuelve productos con nombre y pricing @catalog @critico",
      "status": "failed",
      "duration": 49928
    },
    {
      "title": "sonrie: C3-15 Cupon invalido muestra error claro",
      "status": "skipped",
      "duration": 13815
    },
    {
      "title": "sonrie: C3-04 Descuento visible en catalogo",
      "status": "failed",
      "duration": 16720
    },
    {
      "title": "sonrie: C3-14 Campo de cupon visible en carro (enableCoupons)",
      "status": "passed",
      "duration": 12887
    },
    {
      "title": "sonrie: C3-02 Detectar productos con precio $0",
      "status": "failed",
      "duration": 16703
    },
    {
      "title": "sonrie: C3-01 Precios visibles en catalogo anonimo (formato CLP)",
      "status": "failed",
      "duration": 16803
    },
    {
      "title": "sonrie: C3-04 Descuento visible en catalogo",
      "status": "failed",
      "duration": 16486
    },
    {
      "title": "sonrie: C3-02 Detectar productos con precio $0",
      "status": "failed",
      "duration": 16452
    },
    {
      "title": "sonrie: C3-01 Precios visibles en catalogo anonimo (formato CLP)",
      "status": "failed",
      "duration": 16413
    },
    {
      "title": "sonrie: C3-03 Precios consistentes catalogo vs carro",
      "status": "passed",
      "duration": 12833
    },
    {
      "title": "sonrie: Pipeline API catálogo devuelve productos con nombre y pricing @catalog @critico",
      "status": "failed",
      "duration": 50267
    },
    {
      "title": "sonrie: PAG-16 Montos en historial no muestran valores negativos confusos",
      "status": "passed",
      "duration": 9485
    },
    {
      "title": "sonrie: PAG-04 Historial de pagos carga correctamente",
      "status": "passed",
      "duration": 9308
    },
    {
      "title": "sonrie: C7-12 /payment-documents carga sin error cuando flag=true",
      "status": "skipped",
      "duration": 9303
    },
    {
      "title": "sonrie: C7-10 Facturas visibles en /orders cuando flag=true",
      "status": "skipped",
      "duration": 9215
    },
    {
      "title": "sonrie: C7-11 Opción de facturas en menú lateral cuando flag=true",
      "status": "skipped",
      "duration": 9180
    },
    {
      "title": "sonrie: C7-INV /payment-documents no accesible cuando flag=false",
      "status": "passed",
      "duration": 9538
    },
    {
      "title": "sonrie: Historial de pedidos carga @orders @funcional",
      "status": "passed",
      "duration": 12553
    },
    {
      "title": "sonrie: C7-INV Link \"Mis documentos\" oculto cuando flag=false",
      "status": "passed",
      "duration": 11369
    }
  ]
}