{
  "running": true,
  "startTime": "2026-04-17T18:55:41.163Z",
  "total": 106,
  "passed": 69,
  "failed": 1,
  "skipped": 3,
  "currentTest": null,
  "recentTests": [
    {
      "title": "sonrie: PM1-02 Cupón válido aplica descuento",
      "status": "skipped",
      "duration": 9273
    },
    {
      "title": "sonrie: enableNewUI=false",
      "status": "passed",
      "duration": 7722
    },
    {
      "title": "sonrie: suggestions.hide=true",
      "status": "passed",
      "duration": 7621
    },
    {
      "title": "sonrie: enableBetaButtons=false",
      "status": "passed",
      "duration": 4654
    },
    {
      "title": "sonrie: useNewPromotions=false",
      "status": "passed",
      "duration": 4696
    },
    {
      "title": "sonrie: blockedClientAlert.enableBlockedClientAlert=false",
      "status": "passed",
      "duration": 4429
    },
    {
      "title": "sonrie: externalAccess=true",
      "status": "passed",
      "duration": 4464
    },
    {
      "title": "sonrie: showMinOne=false",
      "status": "passed",
      "duration": 4646
    },
    {
      "title": "sonrie: enableCreditNotes=false",
      "status": "passed",
      "duration": 4538
    },
    {
      "title": "sonrie: enableTask=false",
      "status": "passed",
      "duration": 4512
    },
    {
      "title": "sonrie: pointsEnabled=false",
      "status": "passed",
      "duration": 4528
    },
    {
      "title": "sonrie: paymentsWithoutAccount=false",
      "status": "passed",
      "duration": 6719
    },
    {
      "title": "sonrie: pendingDocuments=false",
      "status": "passed",
      "duration": 4549
    },
    {
      "title": "sonrie: payment.enableNewPaymentModule=false",
      "status": "passed",
      "duration": 7249
    },
    {
      "title": "sonrie: discountTypes.enableOrderDiscountType=false",
      "status": "passed",
      "duration": 8330
    },
    {
      "title": "sonrie: hasTransferPaymentType=false",
      "status": "passed",
      "duration": 7282
    },
    {
      "title": "sonrie: discountTypes.enableProductDiscountType=false",
      "status": "passed",
      "duration": 4579
    },
    {
      "title": "sonrie: taxes.showSummary=true",
      "status": "passed",
      "duration": 7381
    },
    {
      "title": "sonrie: includeTaxRateInPrices=false",
      "status": "passed",
      "duration": 5972
    },
    {
      "title": "sonrie: enableSellerDiscount=false",
      "status": "passed",
      "duration": 8190
    }
  ]
}